MANIFEST.in
README.md
setup.cfg
setup.py
versioneer.py
pummeler/__init__.py
pummeler/_version.py
pummeler/cli.py
pummeler/featurize.py
pummeler/misc.py
pummeler/my_proc.py
pummeler/reader.py
pummeler/sort.py
pummeler/stats.py
pummeler.egg-info/PKG-INFO
pummeler.egg-info/SOURCES.txt
pummeler.egg-info/dependency_links.txt
pummeler.egg-info/entry_points.txt
pummeler.egg-info/requires.txt
pummeler.egg-info/top_level.txt
pummeler.egg-info/zip-safe
pummeler/data/2012-by-region-puma10s.csv.gz
pummeler/data/2012-by-region.csv.gz
pummeler/data/__init__.py
pummeler/data/county-to-puma.meta
pummeler/data/county-to-puma00.csv.gz
pummeler/data/county-to-puma10.csv.gz
pummeler/data/fod_cats.csv
pummeler/data/regions.h5