Metadata-Version: 1.0
Name: pummeler
Version: 0.3.0
Summary: Utilities for processing and analyzing ACS PUMS files.
Home-page: https://github.com/dougalsutherland/pummeler/
Author: Dougal J. Sutherland
Author-email: dougal@gmail.com
License: MIT
Platform: UNKNOWN
